{
	"required": true,
	"package": "com.github.leawind.thirdperson.mixin",
	"compatibilityLevel": "JAVA_17",
	"minVersion": "0.8",
	"client": [
		"CameraInvoker",
		"ClientLevelInvoker",
		"GameRendererInvoker",
		"CameraTypeMixin",
		"LevelRendererMixin",
		"LocalPlayerMixin",
		"ModelPartCubeMixin",
		"RenderTypeMixin",
		"MinecraftMixin",
		"GuiMixin",
		"KeyboardInputMixin",
		"MouseHandlerMixin",
		"EntityMixin",
		"GameRendererMixin",
		"MouseHandlerMixin"
	],
	"mixins": [],
	"injectors": {
		"defaultRequire": 1
	}
}
